certstream_analytics/__init__.py
certstream_analytics/stream.py
certstream_analytics/analysers/__init__.py
certstream_analytics/analysers/base.py
certstream_analytics/analysers/common_domain_analyser.py
certstream_analytics/analysers/domain_matching.py
certstream_analytics/reporters/__init__.py
certstream_analytics/reporters/base.py
certstream_analytics/storages/__init__.py
certstream_analytics/storages/base.py
certstream_analytics/storages/elasticsearch_storage.py
certstream_analytics/transformers/__init__.py
certstream_analytics/transformers/base.py
certstream_analytics-0.1.7.data/scripts/domain_matching.py
certstream_analytics-0.1.7.dist-info/LICENSE
certstream_analytics-0.1.7.dist-info/METADATA
certstream_analytics-0.1.7.dist-info/WHEEL
certstream_analytics-0.1.7.dist-info/dependency_links.txt
certstream_analytics-0.1.7.dist-info/top_level.txt
certstream_analytics-0.1.7.dist-info/RECORD
