Metadata-Version: 2.1
Name: certstream-analytics
Version: 0.1.7
Summary: certstream + analytics
Home-page: https://github.com/huydhn/certstream-analytics
Author: Huy Do
Author-email: huydhn@gmail.com
License: MIT
Platform: UNKNOWN
Classifier: Programming Language :: Python :: 3
Classifier: License :: OSI Approved :: MIT License
Classifier: Operating System :: OS Independent
Requires-Dist: elasticsearch-dsl
Requires-Dist: certstream
Requires-Dist: pyahocorasick
Requires-Dist: tldextract
Requires-Dist: wordsegment
Requires-Dist: pyenchant
Requires-Dist: idna
Requires-Dist: confusable-homoglyphs
